botoenv/__init__.py
botoenv/main.py
botoenv-1.0.0.dist-info/LICENSE
botoenv-1.0.0.dist-info/METADATA
botoenv-1.0.0.dist-info/WHEEL
botoenv-1.0.0.dist-info/entry_points.txt
botoenv-1.0.0.dist-info/top_level.txt
botoenv-1.0.0.dist-info/RECORD
